{
  "commands": [],
  "generated_at": "2026-06-28T21:42:44.566922+00:00",
  "ok": true,
  "repo": "/Users/eric/GitHub/ChatTLA/ChatTLA",
  "scan": {
    "findings": [],
    "include_untracked_scripts": true,
    "ok": true,
    "patterns": [
      "private_tailscale_or_lan_ip",
      "private_ssh_user",
      "private_home_path",
      "site_storage_path",
      "fixed_pbs_account",
      "private_control_socket",
      "specific_compute_node",
      "aisec_specific_host"
    ]
  },
  "tests_ran": false
}
